tree_sitter_muttrc-0.0.6.dist-info/RECORD
tree_sitter_muttrc-0.0.6.dist-info/top_level.txt
tree_sitter_muttrc-0.0.6.dist-info/WHEEL
tree_sitter_muttrc-0.0.6.dist-info/METADATA
tree_sitter_muttrc/__init__.pyi
tree_sitter_muttrc/_binding.abi3.so
tree_sitter_muttrc/__init__.py
tree_sitter_muttrc/binding.c
tree_sitter_muttrc/py.typed
