Metadata-Version: 2.1
Name: tree-sitter-muttrc
Version: 0.0.6
Summary: Muttrc grammar for tree-sitter
License: MIT
Project-URL: Homepage, https://github.com/tree-sitter/tree-sitter-muttrc
Keywords: incremental,parsing,tree-sitter,muttrc
Classifier: Intended Audience :: Developers
Classifier: License :: OSI Approved :: MIT License
Classifier: Topic :: Software Development :: Compilers
Classifier: Topic :: Text Processing :: Linguistic
Classifier: Typing :: Typed
Requires-Python: >=3.8
Provides-Extra: core
Requires-Dist: tree-sitter ~=0.21 ; extra == 'core'
